bbpmf/__init__.py
bbpmf/betabinom_pmf.py
bbpmf-0.0.3.dist-info/LICENSE
bbpmf-0.0.3.dist-info/METADATA
bbpmf-0.0.3.dist-info/WHEEL
bbpmf-0.0.3.dist-info/top_level.txt
bbpmf-0.0.3.dist-info/RECORD
