Metadata-Version: 2.1
Name: bbpmf
Version: 0.0.3
Summary: Probability mass function for a beta-binomial distribution
Home-page: https://gitlab.com/aaylward/bbpmf
Author: Anthony Aylward
Author-email: aaylward@salk.edu
License: UNKNOWN
Platform: UNKNOWN
Classifier: Programming Language :: Python :: 3
Classifier: License :: OSI Approved :: MIT License
Classifier: Operating System :: OS Independent
License-File: LICENSE
Requires-Dist: scipy
